setup.py
graphcore/__init__.py
graphcore/call_graph.py
graphcore/call_graph_test.py
graphcore/clause.py
graphcore/clause_test.py
graphcore/conftest.py
graphcore/conftest_test.py
graphcore/equality_mixin.py
graphcore/equality_mixin_test.py
graphcore/graphcore.py
graphcore/graphcore_sql_integration_test.py
graphcore/graphcore_test.py
graphcore/optimize_constrain_sql_queries.py
graphcore/optimize_reduce_like_parent_child.py
graphcore/optimize_reduce_like_parent_child_test.py
graphcore/optimize_reduce_like_siblings.py
graphcore/optimize_reduce_like_siblings_test.py
graphcore/path.py
graphcore/path_test.py
graphcore/query.py
graphcore/query_plan.py
graphcore/query_plan_test.py
graphcore/query_planner.py
graphcore/query_test.py
graphcore/reflect_class.py
graphcore/reflect_class_test.py
graphcore/reflect_module.py
graphcore/reflect_module_test.py
graphcore/relation.py
graphcore/relation_test.py
graphcore/result_set.py
graphcore/result_set_test.py
graphcore/rule.py
graphcore/rule_test.py
graphcore/sql_query.py
graphcore/sql_query_test.py
graphcore/sql_reflect.py
graphcore/sql_reflect_test.py
graphcore/sql_rules.py
graphcore/test_harness.py
graphcore/test_module.py
graphcore.egg-info/PKG-INFO
graphcore.egg-info/SOURCES.txt
graphcore.egg-info/dependency_links.txt
graphcore.egg-info/requires.txt
graphcore.egg-info/top_level.txt