Metadata-Version: 1.0
Name: graphcore
Version: 0.8.14
Summary: Graphcore is a python library which allows you to query a graph structure with a query language similar to MQL, Falcor or GraphQL
Home-page: http://github.com/dwiel/graphcore
Author: Zach Dwiel
Author-email: zdwiel@gmail.com
License: Apache
Platform: UNKNOWN
